artoolpy
