Metadata-Version: 1.1
Name: artoolpy
Version: 1.317
Summary: Initial version
Home-page: https://gythaogg.github.io
Author: Gytha Ogg
Author-email: gythaoggscat@gmail.com
License: MIT
Platform: linux
Platform: windows
Classifier: Development Status :: 3 - Alpha
Classifier: Topic :: Software Development :: Build Tools
Classifier: License :: OSI Approved :: MIT License
Classifier: Programming Language :: Python :: 2
Classifier: Programming Language :: Python :: 3
